[{
    "display_name": "Playback",
    "extensions": [{
        "author": "Boris Schaedler",
        "display_name": "it'roXs!",
        "description": "Roon Extension for Android App it'roXs!",
        "repository": {
            "type": "git",
            "url": "https://github.com/bsc101/roon-extension-itroxs.git"
        }
    }]
},
{
    "display_name": "Device Control",
    "extensions": [{
        "author": "Doc Bobo",
        "display_name": "Denon/Marantz AVR",
        "description": "Roon Volume Control Extension for Denon/Marantz AV receivers",
        "repository": {
            "type": "git",
            "url": "https://github.com/docbobo/roon-extension-denon.git"
        }
    },
    {
        "author": "Doc Bobo",
        "display_name": "Arcam AVR390/550/850/AV860/SR250",
        "description": "Roon Volume Control Extension for Arcam AVR390/550/850/AV860/SR250 receivers",
        "repository": {
            "type": "git",
            "url": "https://github.com/docbobo/roon-extension-arcam.git"
        }
    },
    {
        "author": "Boris Schaedler",
        "display_name": "Rotel Amps (IP Control)",
        "description": "Roon Volume/Source Control Extension to control Rotel amps via network",
        "repository": {
            "type": "git",
            "url": "https://github.com/bsc101/roon-extension-rotel.git"
        }
    },
    {
        "author": "Marcel van der Veldt",
        "display_name": "Onkyo/Pioneer AVR",
        "description": "Volume Control extension to control Onkyo/Pioneer AV receivers\nvia network",
        "repository": {
            "type": "git",
            "url": "https://github.com/marcelveldt/roon-extension-onkyo.git"
        }
    }]
},
{
    "display_name": "Remote Control",
    "extensions": [{
        "author": "Doc Bobo",
        "display_name": "Logitech Harmony",
        "description": "Roon Source Control Extension to control Logitech Harmony activities",
        "repository": {
            "type": "git",
            "url": "https://github.com/docbobo/roon-extension-harmony.git"
        }
    }]
},
{
    "display_name": "Web / Connectivity",
    "extensions": [{
        "author": "Mike Plugge",
        "display_name": "Web Controller",
        "description": "Roon Extension which provides a web interface based remote",
        "repository": {
            "type": "git",
            "url": "https://github.com/pluggemi/roon-web-controller.git"
        }
    },
    {
        "author": "Varun Randery",
        "display_name": "RESTful Roon Remote",
        "description": "Control Roon using HTTP GET requests from any device",
        "repository": {
            "type": "git",
            "url": "https://github.com/varunrandery/roon-remote.git"
        }
    },
    {
        "author": "David 'Nugget' McNett",
        "display_name": "Community DJ",
        "description": "Synchronize playback among multiple Roon Cores",
        "repository": {
            "type": "git",
            "url": "https://github.com/nugget/roon-community-dj.git"
        }
    }]
}]
